slo_yaml_generator/__init__.py
slo_yaml_generator/main.py
slo_yaml_generator/templates/__init__.py
slo_yaml_generator/templates/alert_policy.yaml.j2
slo_yaml_generator/templates/cloudwatch-slo.yaml.j2
slo_yaml_generator/templates/dynatrace-slo.yaml.j2
slo_yaml_generator/templates/project.yaml.j2
slo_yaml_generator/templates/service.yaml.j2
slo_yaml_generator-0.0.9.dist-info/LICENSE
slo_yaml_generator-0.0.9.dist-info/METADATA
slo_yaml_generator-0.0.9.dist-info/WHEEL
slo_yaml_generator-0.0.9.dist-info/entry_points.txt
slo_yaml_generator-0.0.9.dist-info/top_level.txt
slo_yaml_generator-0.0.9.dist-info/RECORD
