Metadata-Version: 2.1
Name: slo_yaml_generator
Version: 0.0.9
Summary: Generate OpenSLO and Nobl9 yaml configuration
Home-page: https://github.com/jackmford/slo-yaml-generator
Author: Jack Fordyce
Author-email: jackmitchellfordyce@gmail.com
Classifier: Programming Language :: Python :: 3
Classifier: License :: OSI Approved :: MIT License
Classifier: Operating System :: OS Independent
Requires-Python: >=3.6
License-File: LICENSE
Requires-Dist: Jinja2==3.1.4
Requires-Dist: MarkupSafe==2.1.5
